Metadata-Version: 2.1
Name: investimentpy-santeriogouveia
Version: 1.0.2
Summary: Uma biblioteca para análise de investimentos
Home-page: https://github.com/tadrianonet/investimentpy
Author: Thiago S Adriano - Santerio Gouveia
Author-email: santeriogouveia@sefaz.al.gov.br
License: MIT
Platform: UNKNOWN
